pinger_mqtt.py
pinger_mqtt-0.1.0.dist-info/LICENCE
pinger_mqtt-0.1.0.dist-info/METADATA
pinger_mqtt-0.1.0.dist-info/WHEEL
pinger_mqtt-0.1.0.dist-info/entry_points.txt
pinger_mqtt-0.1.0.dist-info/RECORD
