Metadata-Version: 2.1
Name: pinger-mqtt
Version: 0.1.0
Summary: a CLI app to ping IP-Address then send the status via MQTT
License: MIT
Author: muflih
Author-email: nurfaizimuflih10@gmail.com
Requires-Python: >=3.12,<4.0
Classifier: License :: OSI Approved :: MIT License
Classifier: Programming Language :: Python :: 3
Classifier: Programming Language :: Python :: 3.12
Classifier: Programming Language :: Python :: 3.13
Requires-Dist: click (>=8.1,<9.0)
Requires-Dist: paho-mqtt (>=1.6,<2.0)
Requires-Dist: rich (>=13.3,<14.0)
Requires-Dist: rich-click (>=1.6,<2.0)
Requires-Dist: schedule (>=1.1,<2.0)
